LICENSE.txt
MANIFEST.in
README.txt
TODO.txt
setup.py
gloopy/__init__.py
gloopy/color.py
gloopy/gameitem.py
gloopy/gloopy.py
gloopy/version.py
gloopy/world.py
gloopy.egg-info/PKG-INFO
gloopy.egg-info/SOURCES.txt
gloopy.egg-info/dependency_links.txt
gloopy.egg-info/top_level.txt
gloopy/data/shaders/flat.frag
gloopy/data/shaders/flat.vert
gloopy/data/shaders/lighting.frag
gloopy/data/shaders/lighting.vert
gloopy/docs/html/genindex.html
gloopy/docs/html/index.html
gloopy/docs/html/intro.html
gloopy/docs/html/py-modindex.html
gloopy/docs/html/search.html
gloopy/docs/html/searchindex.js
gloopy/docs/html/worked-example.html
gloopy/docs/html/_images/screenshot-simple-cube.png
gloopy/docs/html/_modules/index.html
gloopy/docs/html/_modules/gloopy/color.html
gloopy/docs/html/_modules/gloopy/gameitem.html
gloopy/docs/html/_modules/gloopy/gloopy.html
gloopy/docs/html/_modules/gloopy/world.html
gloopy/docs/html/_modules/gloopy/geom/matrix.html
gloopy/docs/html/_modules/gloopy/geom/orientation.html
gloopy/docs/html/_modules/gloopy/geom/vector.html
gloopy/docs/html/_modules/gloopy/geom/tests/test_matrix.html
gloopy/docs/html/_modules/gloopy/geom/tests/test_orientation.html
gloopy/docs/html/_modules/gloopy/geom/tests/test_vector.html
gloopy/docs/html/_modules/gloopy/move/newtonian.html
gloopy/docs/html/_modules/gloopy/move/orbit.html
gloopy/docs/html/_modules/gloopy/move/spin.html
gloopy/docs/html/_modules/gloopy/shapes/cube.html
gloopy/docs/html/_modules/gloopy/shapes/cube_groups.html
gloopy/docs/html/_modules/gloopy/shapes/dodecahedron.html
gloopy/docs/html/_modules/gloopy/shapes/extrude.html
gloopy/docs/html/_modules/gloopy/shapes/icosahedron.html
gloopy/docs/html/_modules/gloopy/shapes/multishape.html
gloopy/docs/html/_modules/gloopy/shapes/normalize.html
gloopy/docs/html/_modules/gloopy/shapes/octahedron.html
gloopy/docs/html/_modules/gloopy/shapes/ring.html
gloopy/docs/html/_modules/gloopy/shapes/shape.html
gloopy/docs/html/_modules/gloopy/shapes/shape_to_glyph.html
gloopy/docs/html/_modules/gloopy/shapes/stellate.html
gloopy/docs/html/_modules/gloopy/shapes/subdivide.html
