Metadata-Version: 1.0
Name: gloopy
Version: 0.1.3a
Summary: 
Home-page: http://bitbucket.org/tartley/gloopy
Author: Jonathan Hartley
Author-email: tartley@tartley.com
License: New BSD
Platform: UNKNOWN
Classifier: Development Status :: 3 - Alpha
Classifier: Intended Audience :: Developers
Classifier: License :: OSI Approved :: BSD License
Classifier: Operating System :: Microsoft :: Windows
Classifier: Programming Language :: Python :: 2.7
